[{"data":"01/01/2004","valor":"5593"},{"data":"01/02/2004","valor":"5461"},{"data":"01/03/2004","valor":"5529"},{"data":"01/04/2004","valor":"5781"},{"data":"01/05/2004","valor":"6144"},{"data":"01/06/2004","valor":"6015"},{"data":"01/07/2004","valor":"6008"},{"data":"01/08/2004","valor":"6349"},{"data":"01/09/2004","valor":"6315"},{"data":"01/10/2004","valor":"6001"},{"data":"01/11/2004","valor":"5722"},{"data":"01/12/2004","valor":"5541"},{"data":"01/01/2005","valor":"5508"},{"data":"01/02/2005","valor":"5597"},{"data":"01/03/2005","valor":"5581"},{"data":"01/04/2005","valor":"5494"},{"data":"01/05/2005","valor":"5521"},{"data":"01/06/2005","valor":"5640"},{"data":"01/07/2005","valor":"5687"},{"data":"01/08/2005","valor":"5489"},{"data":"01/09/2005","valor":"5517"},{"data":"01/10/2005","valor":"5725"},{"data":"01/11/2005","valor":"5741"},{"data":"01/12/2005","valor":"6179"},{"data":"01/01/2006","valor":"5971"},{"data":"01/02/2006","valor":"5937"},{"data":"01/03/2006","valor":"6175"},{"data":"01/04/2006","valor":"6312"},{"data":"01/05/2006","valor":"6421"},{"data":"01/06/2006","valor":"6548"},{"data":"01/07/2006","valor":"6577"},{"data":"01/08/2006","valor":"6604"},{"data":"01/09/2006","valor":"6955"},{"data":"01/10/2006","valor":"7149"},{"data":"01/11/2006","valor":"7361"},{"data":"01/12/2006","valor":"7934"},{"data":"01/01/2007","valor":"8040"},{"data":"01/02/2007","valor":"7966"},{"data":"01/03/2007","valor":"7960"},{"data":"01/04/2007","valor":"8044"},{"data":"01/05/2007","valor":"8301"},{"data":"01/06/2007","valor":"8556"},{"data":"01/07/2007","valor":"8606"},{"data":"01/08/2007","valor":"9087"},{"data":"01/09/2007","valor":"9330"},{"data":"01/10/2007","valor":"9464"},{"data":"01/11/2007","valor":"9834"},{"data":"01/12/2007","valor":"10284"},{"data":"01/01/2008","valor":"10288"},{"data":"01/02/2008","valor":"10713"},{"data":"01/03/2008","valor":"11267"},{"data":"01/04/2008","valor":"11813"},{"data":"01/05/2008","valor":"12134"},{"data":"01/06/2008","valor":"12064"},{"data":"01/07/2008","valor":"11795"},{"data":"01/08/2008","valor":"12146"},{"data":"01/09/2008","valor":"12224"},{"data":"01/10/2008","valor":"12529"},{"data":"01/11/2008","valor":"12549"},{"data":"01/12/2008","valor":"12111"},{"data":"01/01/2009","valor":"12081"},{"data":"01/02/2009","valor":"12006"},{"data":"01/03/2009","valor":"11916"},{"data":"01/04/2009","valor":"11734"},{"data":"01/05/2009","valor":"11677"},{"data":"01/06/2009","valor":"10852"},{"data":"01/07/2009","valor":"10809"},{"data":"01/08/2009","valor":"11104"},{"data":"01/09/2009","valor":"11037"},{"data":"01/10/2009","valor":"11238"},{"data":"01/11/2009","valor":"11329"},{"data":"01/12/2009","valor":"11769"},{"data":"01/01/2010","valor":"11863"},{"data":"01/02/2010","valor":"11807"},{"data":"01/03/2010","valor":"11892"},{"data":"01/04/2010","valor":"11798"},{"data":"01/05/2010","valor":"12245"},{"data":"01/06/2010","valor":"12602"},{"data":"01/07/2010","valor":"12981"},{"data":"01/08/2010","valor":"13382"},{"data":"01/09/2010","valor":"13575"},{"data":"01/10/2010","valor":"13872"},{"data":"01/11/2010","valor":"14831"},{"data":"01/12/2010","valor":"14981"},{"data":"01/01/2011","valor":"14847"},{"data":"01/02/2011","valor":"15247"},{"data":"01/03/2011","valor":"15891"},{"data":"01/04/2011","valor":"16002"},{"data":"01/05/2011","valor":"16026"},{"data":"01/06/2011","valor":"14776"},{"data":"01/07/2011","valor":"14968"},{"data":"01/08/2011","valor":"15199"},{"data":"01/09/2011","valor":"15863"},{"data":"01/10/2011","valor":"16189"},{"data":"01/11/2011","valor":"16732"},{"data":"01/12/2011","valor":"16908"},{"data":"01/01/2012","valor":"18845"},{"data":"01/02/2012","valor":"19005"},{"data":"01/03/2012","valor":"19190"},{"data":"01/04/2012","valor":"19124"},{"data":"01/05/2012","valor":"18968"},{"data":"01/06/2012","valor":"19197"},{"data":"01/07/2012","valor":"19121"},{"data":"01/08/2012","valor":"19005"},{"data":"01/09/2012","valor":"19409"},{"data":"01/10/2012","valor":"19528"},{"data":"01/11/2012","valor":"19701"},{"data":"01/12/2012","valor":"20189"},{"data":"01/01/2013","valor":"19475"},{"data":"01/02/2013","valor":"19885"},{"data":"01/03/2013","valor":"20344"},{"data":"01/04/2013","valor":"20871"},{"data":"01/05/2013","valor":"21222"},{"data":"01/06/2013","valor":"21126"},{"data":"01/07/2013","valor":"20802"},{"data":"01/08/2013","valor":"21307"},{"data":"01/09/2013","valor":"21559"},{"data":"01/10/2013","valor":"21740"},{"data":"01/11/2013","valor":"22049"},{"data":"01/12/2013","valor":"22386"},{"data":"01/01/2014","valor":"22381"},{"data":"01/02/2014","valor":"22881"},{"data":"01/03/2014","valor":"23015"},{"data":"01/04/2014","valor":"23071"},{"data":"01/05/2014","valor":"23061"},{"data":"01/06/2014","valor":"23161"},{"data":"01/07/2014","valor":"23072"},{"data":"01/08/2014","valor":"23165"},{"data":"01/09/2014","valor":"23371"},{"data":"01/10/2014","valor":"23478"},{"data":"01/11/2014","valor":"23757"},{"data":"01/12/2014","valor":"24318"},{"data":"01/01/2015","valor":"23929"},{"data":"01/02/2015","valor":"23719"},{"data":"01/03/2015","valor":"23721"},{"data":"01/04/2015","valor":"23779"},{"data":"01/05/2015","valor":"23537"},{"data":"01/06/2015","valor":"23496"},{"data":"01/07/2015","valor":"23346"},{"data":"01/08/2015","valor":"23583"},{"data":"01/09/2015","valor":"23504"},{"data":"01/10/2015","valor":"23545"},{"data":"01/11/2015","valor":"23634"},{"data":"01/12/2015","valor":"24082"},{"data":"01/01/2016","valor":"23678"},{"data":"01/02/2016","valor":"23202"},{"data":"01/03/2016","valor":"22769"},{"data":"01/04/2016","valor":"22471"},{"data":"01/05/2016","valor":"22324"},{"data":"01/06/2016","valor":"21845"},{"data":"01/07/2016","valor":"21805"},{"data":"01/08/2016","valor":"21718"},{"data":"01/09/2016","valor":"21555"},{"data":"01/10/2016","valor":"21351"},{"data":"01/11/2016","valor":"21322"},{"data":"01/12/2016","valor":"21106"},{"data":"01/01/2017","valor":"20863"},{"data":"01/02/2017","valor":"20905"},{"data":"01/03/2017","valor":"20428"},{"data":"01/04/2017","valor":"20085"},{"data":"01/05/2017","valor":"19711"},{"data":"01/06/2017","valor":"19830"},{"data":"01/07/2017","valor":"18869"},{"data":"01/08/2017","valor":"18850"},{"data":"01/09/2017","valor":"19103"},{"data":"01/10/2017","valor":"18471"},{"data":"01/11/2017","valor":"18898"},{"data":"01/12/2017","valor":"19273"},{"data":"01/01/2018","valor":"18898"},{"data":"01/02/2018","valor":"19846"},{"data":"01/03/2018","valor":"21124"},{"data":"01/04/2018","valor":"20383"},{"data":"01/05/2018","valor":"19495"},{"data":"01/06/2018","valor":"18981"},{"data":"01/07/2018","valor":"19052"},{"data":"01/08/2018","valor":"19222"},{"data":"01/09/2018","valor":"19258"},{"data":"01/10/2018","valor":"19295"},{"data":"01/11/2018","valor":"19989"},{"data":"01/12/2018","valor":"20068"},{"data":"01/01/2019","valor":"19773"},{"data":"01/02/2019","valor":"20172"},{"data":"01/03/2019","valor":"20858"}]